fdnubank/__init__.py
fdnubank/auth_mode.py
fdnubank/cli.py
fdnubank/exception.py
fdnubank/nubank.py
fdnubank/queries/account_balance.gql
fdnubank/queries/account_feed.gql
fdnubank/queries/account_feed_paginated.gql
fdnubank/queries/account_id.gql
fdnubank/queries/account_investments.gql
fdnubank/queries/account_investments_yield.gql
fdnubank/queries/account_savings.gql
fdnubank/queries/create_boleto.gql
fdnubank/queries/create_money_request.gql
fdnubank/queries/create_pix_money_request.gql
fdnubank/queries/get_pix_keys.gql
fdnubank/queries/pix_receipt_screen.gql
fdnubank/utils/__init__.py
fdnubank/utils/certificate_generator.py
fdnubank/utils/discovery.py
fdnubank/utils/graphql.py
fdnubank/utils/http.py
fdnubank/utils/parsing.py
fdnubank-0.1.5.dist-info/METADATA
fdnubank-0.1.5.dist-info/WHEEL
fdnubank-0.1.5.dist-info/RECORD
